ipttrace/main.py
ipttrace-0.2.5.dist-info/METADATA
ipttrace-0.2.5.dist-info/WHEEL
ipttrace-0.2.5.dist-info/entry_points.txt
ipttrace-0.2.5.dist-info/RECORD
