Metadata-Version: 2.1
Name: ipttrace
Version: 0.2.5
Summary: A CLI Helps You Trace Iptables Rules at Ease
Home-page: https://github.com/sieginglion/ipttrace
Author: sieginglion
Author-email: sieginglion@gmail.com
Requires-Python: >=3.6.3,<4.0.0
Classifier: Programming Language :: Python :: 3
Classifier: Programming Language :: Python :: 3.7
Classifier: Programming Language :: Python :: 3.8
Classifier: Programming Language :: Python :: 3.9
Classifier: Programming Language :: Python :: 3.10
Classifier: Programming Language :: Python :: 3.11
Requires-Dist: dataclasses (>=0.8,<0.9) ; python_version < "3.7"
Requires-Dist: rich (>=12.6.0,<13.0.0)
Requires-Dist: typer (>=0.9.0,<0.10.0)
Project-URL: Repository, https://github.com/sieginglion/ipttrace
